{
    "url": "https://cdn.shopify.com/s/files/1/0050/7478/0275/products/61b175ee-d04f-4e69-b9d6-c8c5f0cc6205_c1ea2544-7bba-4f95-a7a5-991ddcb2c725.jpg?v=1629712607",
    "key": "000010462",
    "status": "success",
    "error_message": null,
    "width": 256,
    "height": 256,
    "original_width": 1280,
    "original_height": 960,
    "exif": "{\"Image Orientation\": \"Horizontal (normal)\", \"Image XResolution\": \"72\", \"Image YResolution\": \"72\", \"Image ResolutionUnit\": \"Pixels/Inch\", \"Image YCbCrPositioning\": \"Centered\", \"Image ExifOffset\": \"102\", \"EXIF ExifVersion\": \"\", \"EXIF ComponentsConfiguration\": \"\", \"EXIF FlashPixVersion\": \"\", \"EXIF ColorSpace\": \"Uncalibrated\", \"EXIF ExifImageWidth\": \"1280\", \"EXIF ExifImageLength\": \"960\"}",
    "md5": "cbc664367edbcfe15fbe7764b67f1824"
}