{
    "url": "https://cdn.shopify.com/s/files/1/0050/7478/0275/products/mw2MyE7gCg.jpg?v=1649943814",
    "key": "000012616",
    "status": "success",
    "error_message": null,
    "width": 256,
    "height": 256,
    "original_width": 3601,
    "original_height": 3601,
    "exif": "{\"Image Orientation\": \"Horizontal (normal)\", \"Image XResolution\": \"96\", \"Image YResolution\": \"96\", \"Image ResolutionUnit\": \"Pixels/Inch\", \"Image YCbCrPositioning\": \"Centered\", \"Image ExifOffset\": \"102\", \"EXIF ExifVersion\": \"\", \"EXIF ComponentsConfiguration\": \"\", \"EXIF FlashPixVersion\": \"\", \"EXIF ColorSpace\": \"Uncalibrated\", \"EXIF ExifImageWidth\": \"3601\", \"EXIF ExifImageLength\": \"3601\"}",
    "md5": "7d8461ddd1d2bbe368f9d9ef56838b39"
}