{
    "url": "https://cdn.shopify.com/s/files/1/0050/7478/0275/products/IMG_6712.jpg?v=1636561481",
    "key": "000012060",
    "status": "success",
    "error_message": null,
    "width": 256,
    "height": 256,
    "original_width": 2621,
    "original_height": 3931,
    "exif": "{\"Image Orientation\": \"Horizontal (normal)\", \"Image XResolution\": \"72\", \"Image YResolution\": \"72\", \"Image ResolutionUnit\": \"Pixels/Inch\", \"Image YCbCrPositioning\": \"Centered\", \"Image ExifOffset\": \"102\", \"EXIF ExifVersion\": \"\", \"EXIF ComponentsConfiguration\": \"\", \"EXIF FlashPixVersion\": \"\", \"EXIF ColorSpace\": \"Uncalibrated\", \"EXIF ExifImageWidth\": \"2621\", \"EXIF ExifImageLength\": \"3931\"}",
    "md5": "0ab2bf29cec0bd65ce3f293023f1df82"
}