{
    "url": "https://cdn.shopify.com/s/files/1/0050/7478/0275/products/ENpEdz1t4y.jpg?v=1649943781",
    "key": "000012621",
    "status": "success",
    "error_message": null,
    "width": 256,
    "height": 256,
    "original_width": 1719,
    "original_height": 1719,
    "exif": "{\"Image Orientation\": \"Horizontal (normal)\", \"Image XResolution\": \"96\", \"Image YResolution\": \"96\", \"Image ResolutionUnit\": \"Pixels/Inch\", \"Image YCbCrPositioning\": \"Centered\", \"Image ExifOffset\": \"102\", \"EXIF ExifVersion\": \"\", \"EXIF ComponentsConfiguration\": \"\", \"EXIF FlashPixVersion\": \"\", \"EXIF ColorSpace\": \"Uncalibrated\", \"EXIF ExifImageWidth\": \"1719\", \"EXIF ExifImageLength\": \"1719\"}",
    "md5": "00f73471502f9f5d3032c2c1b4f03f7a"
}