{
    "url": "https://cdn.shopify.com/s/files/1/0050/7478/0275/products/Screenshot_2019-04-12-17-44-02-63_Original.jpg?v=1621328590",
    "key": "000001185",
    "status": "success",
    "error_message": null,
    "width": 256,
    "height": 256,
    "original_width": 1704,
    "original_height": 1704,
    "exif": "{\"Image Orientation\": \"Horizontal (normal)\", \"Image XResolution\": \"72\", \"Image YResolution\": \"72\", \"Image ResolutionUnit\": \"Pixels/Inch\", \"Image YCbCrPositioning\": \"Centered\", \"Image ExifOffset\": \"102\", \"EXIF ExifVersion\": \"\", \"EXIF ComponentsConfiguration\": \"\", \"EXIF FlashPixVersion\": \"\", \"EXIF ColorSpace\": \"Uncalibrated\", \"EXIF ExifImageWidth\": \"1704\", \"EXIF ExifImageLength\": \"1704\"}",
    "md5": "f4cb39f49aa03213c3c2ade4e9ce117b"
}