{
    "url": "https://cdn.shopify.com/s/files/1/0050/7478/0275/products/0x8sya9KG0.jpg?v=1629711123",
    "key": "000000064",
    "status": "success",
    "error_message": null,
    "width": 256,
    "height": 256,
    "original_width": 767,
    "original_height": 767,
    "exif": "{\"Image Orientation\": \"Horizontal (normal)\", \"Image XResolution\": \"96\", \"Image YResolution\": \"96\", \"Image ResolutionUnit\": \"Pixels/Inch\", \"Image YCbCrPositioning\": \"Centered\", \"Image ExifOffset\": \"102\", \"EXIF ExifVersion\": \"\", \"EXIF ComponentsConfiguration\": \"\", \"EXIF FlashPixVersion\": \"\", \"EXIF ColorSpace\": \"Uncalibrated\", \"EXIF ExifImageWidth\": \"767\", \"EXIF ExifImageLength\": \"767\"}",
    "md5": "51cb5dfb33424dda962f8a1ab4ad329f"
}