{
    "url": "https://cdn.shopify.com/s/files/1/0050/7478/0275/products/IMG_20201222_190651_ec4c9ec5-cab1-40eb-a8a2-43bc2a6c2fb5.jpg?v=1629712767",
    "key": "000002836",
    "status": "success",
    "error_message": null,
    "width": 256,
    "height": 256,
    "original_width": 3775,
    "original_height": 3775,
    "exif": "{\"Image Orientation\": \"Horizontal (normal)\", \"Image XResolution\": \"72\", \"Image YResolution\": \"72\", \"Image ResolutionUnit\": \"Pixels/Inch\", \"Image YCbCrPositioning\": \"Centered\", \"Image ExifOffset\": \"102\", \"EXIF ExifVersion\": \"\", \"EXIF ComponentsConfiguration\": \"\", \"EXIF FlashPixVersion\": \"\", \"EXIF ColorSpace\": \"Uncalibrated\", \"EXIF ExifImageWidth\": \"3775\", \"EXIF ExifImageLength\": \"3775\"}",
    "md5": "8fd61235850d5b28cf4c7714b7e0c3a8"
}