{
    "url": "https://cdn.shopify.com/s/files/1/0050/7478/0275/products/baguevenusiceetbagueuranusice_49ff5305-656d-42f4-9e96-9c208df663aa.jpg?v=1631176067",
    "key": "000008649",
    "status": "success",
    "error_message": null,
    "width": 256,
    "height": 256,
    "original_width": 1024,
    "original_height": 1024,
    "exif": "{\"Image Orientation\": \"Horizontal (normal)\", \"Image XResolution\": \"300\", \"Image YResolution\": \"300\", \"Image ResolutionUnit\": \"Pixels/Inch\", \"Image YCbCrPositioning\": \"Centered\", \"Image ExifOffset\": \"102\", \"EXIF ExifVersion\": \"\", \"EXIF ComponentsConfiguration\": \"\", \"EXIF FlashPixVersion\": \"\", \"EXIF ColorSpace\": \"Uncalibrated\", \"EXIF ExifImageWidth\": \"1024\", \"EXIF ExifImageLength\": \"1024\"}",
    "md5": "88364139d66133d5ab58fafdf4b10735"
}