{
    "url": "https://cdn.shopify.com/s/files/1/0050/7478/0275/products/sarelia14juil033Cm-600x600.jpg?v=1646429329",
    "key": "000005458",
    "status": "success",
    "error_message": null,
    "width": 256,
    "height": 256,
    "original_width": 600,
    "original_height": 600,
    "exif": "{\"Image Orientation\": \"Horizontal (normal)\", \"Image XResolution\": \"300\", \"Image YResolution\": \"300\", \"Image ResolutionUnit\": \"Pixels/Inch\", \"Image YCbCrPositioning\": \"Centered\", \"Image ExifOffset\": \"102\", \"EXIF ExifVersion\": \"\", \"EXIF ComponentsConfiguration\": \"\", \"EXIF FlashPixVersion\": \"\", \"EXIF ColorSpace\": \"Uncalibrated\", \"EXIF ExifImageWidth\": \"600\", \"EXIF ExifImageLength\": \"600\"}",
    "md5": "4f702e0c484f8111c93a0e4b11f02f3c"
}