{
    "url": "https://cdn.shopify.com/s/files/1/0050/7478/0275/products/dq8LIvmOHZ.jpg?v=1649708273",
    "key": "000002775",
    "status": "success",
    "error_message": null,
    "width": 256,
    "height": 256,
    "original_width": 3981,
    "original_height": 3981,
    "exif": "{\"Image Orientation\": \"Horizontal (normal)\", \"Image XResolution\": \"96\", \"Image YResolution\": \"96\", \"Image ResolutionUnit\": \"Pixels/Inch\", \"Image YCbCrPositioning\": \"Centered\", \"Image ExifOffset\": \"102\", \"EXIF ExifVersion\": \"\", \"EXIF ComponentsConfiguration\": \"\", \"EXIF FlashPixVersion\": \"\", \"EXIF ColorSpace\": \"Uncalibrated\", \"EXIF ExifImageWidth\": \"3981\", \"EXIF ExifImageLength\": \"3981\"}",
    "md5": "c6c8834a9bc0c926761b0e03fc2a903a"
}