{
    "url": "https://cdn.shopify.com/s/files/1/0050/7478/0275/products/F2OAzV4J68.jpg?v=1629710854",
    "key": "000011297",
    "status": "success",
    "error_message": null,
    "width": 256,
    "height": 256,
    "original_width": 2000,
    "original_height": 2000,
    "exif": "{\"Image Orientation\": \"Horizontal (normal)\", \"Image XResolution\": \"96\", \"Image YResolution\": \"96\", \"Image ResolutionUnit\": \"Pixels/Inch\", \"Image YCbCrPositioning\": \"Centered\", \"Image ExifOffset\": \"102\", \"EXIF ExifVersion\": \"\", \"EXIF ComponentsConfiguration\": \"\", \"EXIF FlashPixVersion\": \"\", \"EXIF ColorSpace\": \"Uncalibrated\", \"EXIF ExifImageWidth\": \"2000\", \"EXIF ExifImageLength\": \"2000\"}",
    "md5": "a7d4d6fa6de94fba7e6432b48f7a3fe7"
}