{
    "url": "https://cdn.shopify.com/s/files/1/0050/7478/0275/products/3tPxVTB1fJ.jpg?v=1629709313",
    "key": "000005829",
    "status": "success",
    "error_message": null,
    "width": 256,
    "height": 256,
    "original_width": 2586,
    "original_height": 2586,
    "exif": "{\"Image Orientation\": \"Horizontal (normal)\", \"Image XResolution\": \"72\", \"Image YResolution\": \"72\", \"Image ResolutionUnit\": \"Pixels/Inch\", \"Image YCbCrPositioning\": \"Centered\", \"Image ExifOffset\": \"102\", \"EXIF ExifVersion\": \"\", \"EXIF ComponentsConfiguration\": \"\", \"EXIF FlashPixVersion\": \"\", \"EXIF ColorSpace\": \"Uncalibrated\", \"EXIF ExifImageWidth\": \"2586\", \"EXIF ExifImageLength\": \"2586\"}",
    "md5": "dbfc7e801661f0226de12ef448c3f7ed"
}