{
    "url": "https://cdn.shopify.com/s/files/1/0050/7478/0275/products/IMG_4488.jpg?v=1636561513",
    "key": "000012051",
    "status": "success",
    "error_message": null,
    "width": 256,
    "height": 256,
    "original_width": 2509,
    "original_height": 3370,
    "exif": "{\"Image Orientation\": \"Horizontal (normal)\", \"Image XResolution\": \"72\", \"Image YResolution\": \"72\", \"Image ResolutionUnit\": \"Pixels/Inch\", \"Image YCbCrPositioning\": \"Centered\", \"Image ExifOffset\": \"102\", \"EXIF ExifVersion\": \"\", \"EXIF ComponentsConfiguration\": \"\", \"EXIF FlashPixVersion\": \"\", \"EXIF ColorSpace\": \"Uncalibrated\", \"EXIF ExifImageWidth\": \"2509\", \"EXIF ExifImageLength\": \"3370\"}",
    "md5": "70294d151c093cd97f30913ac1a51b85"
}