{
    "url": "https://cdn.shopify.com/s/files/1/0050/7478/0275/products/il_794xN.3207030334_l1y1.jpg?v=1633079573",
    "key": "000003934",
    "status": "success",
    "error_message": null,
    "width": 256,
    "height": 256,
    "original_width": 794,
    "original_height": 794,
    "exif": "{\"Image Orientation\": \"Horizontal (normal)\", \"Image XResolution\": \"72\", \"Image YResolution\": \"72\", \"Image ResolutionUnit\": \"Pixels/Inch\", \"Image YCbCrPositioning\": \"Centered\", \"Image ExifOffset\": \"102\", \"EXIF ExifVersion\": \"\", \"EXIF ComponentsConfiguration\": \"\", \"EXIF FlashPixVersion\": \"\", \"EXIF ColorSpace\": \"Uncalibrated\", \"EXIF ExifImageWidth\": \"794\", \"EXIF ExifImageLength\": \"794\"}",
    "md5": "19c307e0df1aa8533760e028376a173a"
}