{
    "url": "https://cdn.shopify.com/s/files/1/0050/7478/0275/products/ULEdbxBsYx.jpg?v=1629713135",
    "key": "000004906",
    "status": "success",
    "error_message": null,
    "width": 256,
    "height": 256,
    "original_width": 2571,
    "original_height": 2571,
    "exif": "{\"Image Orientation\": \"Horizontal (normal)\", \"Image XResolution\": \"96\", \"Image YResolution\": \"96\", \"Image ResolutionUnit\": \"Pixels/Inch\", \"Image YCbCrPositioning\": \"Centered\", \"Image ExifOffset\": \"102\", \"EXIF ExifVersion\": \"\", \"EXIF ComponentsConfiguration\": \"\", \"EXIF FlashPixVersion\": \"\", \"EXIF ColorSpace\": \"Uncalibrated\", \"EXIF ExifImageWidth\": \"2571\", \"EXIF ExifImageLength\": \"2571\"}",
    "md5": "595afbc5a7014d23cc6b18a4eaf728c6"
}