{
    "url": "https://cdn.shopify.com/s/files/1/0050/7478/0275/products/53SfwUcNlW.jpg?v=1629714223",
    "key": "000002378",
    "status": "success",
    "error_message": null,
    "width": 256,
    "height": 256,
    "original_width": 2516,
    "original_height": 2516,
    "exif": "{\"Image Orientation\": \"Horizontal (normal)\", \"Image XResolution\": \"96\", \"Image YResolution\": \"96\", \"Image ResolutionUnit\": \"Pixels/Inch\", \"Image YCbCrPositioning\": \"Centered\", \"Image ExifOffset\": \"102\", \"EXIF ExifVersion\": \"\", \"EXIF ComponentsConfiguration\": \"\", \"EXIF FlashPixVersion\": \"\", \"EXIF ColorSpace\": \"Uncalibrated\", \"EXIF ExifImageWidth\": \"2516\", \"EXIF ExifImageLength\": \"2516\"}",
    "md5": "28e454b4e09474422cf2e8cd827a8957"
}